Metadata-Version: 2.1
Name: foggyday
Version: 1.0.0
Summary: Weather Forcast Data
Home-page: http://jinkosiz.pythonanywhere.com/
Author: Zakhar Sotnichenko
Author-email: zakhar.sotnichenko@mail.ru
License: MIT
Keywords: weather,forecast,openweather
Classifier: Development Status :: 3 - Alpha
Classifier: Intended Audience :: Developers
Classifier: Topic :: Software Development :: Build Tools
Classifier: License :: OSI Approved :: MIT License
Classifier: Programming Language :: Python :: 3.5
Classifier: Programming Language :: Python :: 3.6
Classifier: Programming Language :: Python :: 3.7
Classifier: Programming Language :: Python :: 3.8
Classifier: Programming Language :: Python :: 3.9
Classifier: Programming Language :: Python :: 3.10
